LICENSE.md
README.md
setup.py
HY_sshapi.egg-info/PKG-INFO
HY_sshapi.egg-info/SOURCES.txt
HY_sshapi.egg-info/dependency_links.txt
HY_sshapi.egg-info/requires.txt
HY_sshapi.egg-info/top_level.txt
SSH_Operation/SSH_Operation.py
SSH_Operation/__init__.py
SSH_Operation/forward.py
SSH_Operation/interactive.py