Metadata-Version: 2.1
Name: HY-sshapi
Version: 2022.2.26.1528
Summary: A tool based on paramiko used to connect to remote server.
Author: Hengyue Li
Author-email: hengyue.li@hengyue.li
License: LICENSE.md
Platform: UNKNOWN
License-File: LICENSE.md
